reahl/sqlitesupport.py
reahl_sqlitesupport-7.0.3.dist-info/LICENSE
reahl_sqlitesupport-7.0.3.dist-info/METADATA
reahl_sqlitesupport-7.0.3.dist-info/WHEEL
reahl_sqlitesupport-7.0.3.dist-info/entry_points.txt
reahl_sqlitesupport-7.0.3.dist-info/reahl-component.toml
reahl_sqlitesupport-7.0.3.dist-info/top_level.txt
reahl_sqlitesupport-7.0.3.dist-info/RECORD
