Metadata-Version: 2.1
Name: reahl-sqlitesupport
Version: 7.0.3
Summary: Support for using Sqlite with Reahl.
Author-email: Iwan Vosloo <iwan@reahl.org>, Craig Sparks <craig@reahl.org>
Classifier: Development Status :: 5 - Production/Stable
Classifier: Intended Audience :: Developers
Classifier: License :: OSI Approved
Classifier: Operating System :: OS Independent
Classifier: Programming Language :: Python :: 3
Requires-Python: >=3.8
License-File: LICENSE
Requires-Dist: reahl-component <7.1,>=7.0
